[
  {
    "id": "0",
    "storyTitle": "On se déguise",
    "story": "Il est l'heure de me préparer pour cette soirée de chasse aux bonbons, quel déguisement vais-je choisir?",
    "img": "https://res.cloudinary.com/dxze602g1/image/upload/v1540950614/room.png",
    "btn1": {
      "id": "1",
      "text": "Zombie",
      "avatar": "https://res.cloudinary.com/dxze602g1/image/upload/v1540950603/zombie.png",
      "classText": "avatar-btn",
      "score": "0"
    },
    "btn2": {
      "id": "1",
      "text": "Citrouille",
      "avatar": "https://res.cloudinary.com/dxze602g1/image/upload/v1540973506/pumpkin2.png",
      "classText": "avatar-btn",
      "score": "0"
    }
  },
  {
    "id": "1",
    "storyTitle": "Départ pour l'aventure",
    "story": "Dès la sortie de ma maison, je me retrouve avec un choix crucial, choisir ma direction:",
    "img": "https://res.cloudinary.com/dxze602g1/image/upload/v1540950611/choice.png",
    "btn1": {
      "id": "2",
      "text": "Chemin éclairé",
      "classText": "",
      "score": "10"
    },
    "btn2": {
      "id": "3",
      "text": "Chemin obscur",
      "classText": "",
      "score": "15"
    }
  },
  {
    "id": "2",
    "storyTitle": "Arrivée devant une belle maison",
    "story": "Après avoir sonné, une famille m'ouvre la porte et me propose de choisir entre deux types de bonbons:",
    "img": "https://res.cloudinary.com/dxze602g1/image/upload/v1540950608/porte_vieille.png",
    "btn1": {
      "id": "4",
      "text": "M&M's",
      "classText": "",
      "score": "20"
    },
    "btn2": {
      "id": "4",
      "text": "Fraises Tagada",
      "classText": "",
      "score": "30"
    }
  },
  {
    "id": "3",
    "storyTitle": "Arrivée devant une maison avec une grand-mère ",
    "story": "Je toque à la porte, aucune réponse",
    "img": "https://res.cloudinary.com/dxze602g1/image/upload/v1540950607/maison-vieille.png",
    "btn1": {
      "id": "5",
      "text": "Je toque à nouveau !",
      "classText": "",
      "score": "10"
    },
    "btn2": {
      "id": "6",
      "text": "Je continue mon chemin",
      "classText": "",
      "score": "10"
    }
  },
  {
    "id": "4",
    "storyTitle": "Un choix difficile",
    "story": "Il est 22h20 et demain j'ai un hackathon qui commence, j'hésite à continuer ma chasse ou rentrer un peu me reposer...",
    "img": "https://res.cloudinary.com/dxze602g1/image/upload/v1540950611/choice.png",
    "btn1": {
      "id": "7",
      "text": "Je rentre tranquillou",
      "classText": ""
    },
    "btn2": {
      "id": "8",
      "text": "Je continue mon aventure",
      "classText": ""
    }
  },
  {
    "id": "5",
    "storyTitle": "J'ai retoqué ! ",
    "story": "J'entends que quelqu'un s'approche, une grand mère m'ouvre la porte ATTENTION CECI N'EST PAS TERMINE LOL",
    "img": "https://res.cloudinary.com/dxze602g1/image/upload/v1540950608/porte_hant%C3%A9e.png",
    "btn1": {
      "id": "9",
      "text": "Voilà un chou de bruxelle mon petit ! Et je repars à la chasse aux bonbons !",
      "classText": ""
    },
    "btn2": {
      "id": "10",
      "text": "Bah là t'es mort   A DEFINIR  !",
      "classText": ""
    }
  },
  {
    "id": "6",
    "storyTitle": "L'aventure continue, je suis devant une maison hantée !",
    "story": "XXXXX",
    "img": "https://res.cloudinary.com/dxze602g1/image/upload/v1540950604/haunted-house.png",
    "btn1": {
      "id": "9",
      "text": "Je rentre dedans, même pas peur !"
    },
    "btn2": {
      "id": "10",
      "text": "J'en ai marre de tout ce stress, tcho les nazes je rentre",
      "classText": ""
    }
  },
  {
    "id": "7",
    "storyTitle": "Game Over",
    "story": "Une belle mort.",
    "img": "https://res.cloudinary.com/dxze602g1/image/upload/v1540950603/zombie-alone.png",
    "btn1": {
      "id": "8",
      "text": "pour l'instant je vais à 8",
      "classText": ""
    },
    "btn2": {
      "id": "0",
      "text": "pour l'instant je vais à 0",
      "classText": ""
    }
  },
  {
    "id": "8",
    "storyTitle": "Une nouvelle maison",
    "story": "Après une petite marche dans le quartier, j'arrive à une nouvelle maison. Je frappe à la porte, mais personne ne me répond.",
    "img": "https://res.cloudinary.com/dxze602g1/image/upload/v1540950605/alley.png",
    "btn1": {
      "id": "11",
      "text": "Je décide tout de même d'entrer dans la maison",
      "classText": ""
    },
    "btn2": {
      "id": "7",
      "text": "Je rentre en courant",
      "classText": ""
    }
  },
  {
    "id": "9",
    "storyTitle": "Une autre maison",
    "story": "Si je suis un zombie, je repère un panier de bonbons, je me faufile en faisant le zombie ! Si je suis une citrouille je me fais bouffer",
    "img": "https://res.cloudinary.com/dxze602g1/image/upload/v1540950605/alley.png",
    "btn1": {
      "id": "12",
      "text": "Je me dirige vers une allée abandonnée "
    },
    "btn2": {
      "id": "0",
      "text": "Bah là t'es mort   A DEFINIR  !"
    }
  },
  {
    "id": "10",
    "storyTitle": "Je suis rentré chez moi sans être mort",
    "story": "Je suis rentrée chez moi, normalement de de boutons mais affichage du score avec une phrase",
    "img": "https://res.cloudinary.com/dxze602g1/image/upload/v1540950603/zombie-alone.png",
    "btn1": {
      "id": "0",
      "text": "pour l'instant je vais à 0"
    },
    "btn2": {
      "id": "6",
      "text": "pour l'instant je vais à 6"
    }
  },
  {
    "id": "11",
    "storyTitle": "X",
    "story": "X.",
    "img": "https://res.cloudinary.com/dxze602g1/image/upload/v1540950603/zombie-alone.png",
    "btn1": {
      "id": "12",
      "text": "pour l'instant je vais à 12"
    },
    "btn2": {
      "id": "10",
      "text": "pour l'instant je vais à 10"
    }
  },
  {
    "id": "12",
    "storyTitle": "L'allée de meurtrière",
    "story": "X.",
    "img": "https://res.cloudinary.com/dxze602g1/image/upload/v1540950605/alley.png",
    "btn1": {
      "id": "5",
      "text": "pour l'instant je vais à 5"
    },
    "btn2": {
      "id": "6",
      "text": "pour l'instant je vais à 6"
    }
  }
]
